Nasr
